[
    83,
    1194,
    {
        "accum_grad": 4,
        "adim": 512,
        "aheads": 8,
        "apply_uttmvn": true,
        "backend": "pytorch",
        "badim": 320,
        "batch_bins": 3000000,
        "batch_count": "auto",
        "batch_frames_in": 0,
        "batch_frames_inout": 0,
        "batch_frames_out": 0,
        "batch_size": 0,
        "bdropout_rate": 0.0,
        "beam_size": 4,
        "blayers": 2,
        "bnmask": 2,
        "bprojs": 300,
        "btype": "blstmp",
        "bunits": 300,
        "char_list": [
            "<blank>",
            "<unk>",
            "'",
            "-",
            "13",
            "A",
            "ABL",
            "ABLE",
            "ABLI",
            "ACR",
            "ACT",
            "AD",
            "ADD",
            "ADGE",
            "AGE",
            "AGGE",
            "AID",
            "AIL",
            "AIR",
            "AKE",
            "AKES",
            "AL",
            "ALL",
            "ALLOW",
            "ALS",
            "ALTH",
            "AM",
            "AME",
            "AMENT",
            "AN",
            "ANA",
            "ANCE",
            "AND",
            "ANGE",
            "ANKE",
            "ANNO",
            "ANT",
            "ANTEE",
            "ANY",
            "AP",
            "APPE",
            "AR",
            "ARB",
            "ARE",
            "ARM",
            "ARN",
            "ART",
            "ARTI",
            "ASH",
            "ASK",
            "ASS",
            "AST",
            "AT",
            "ATE",
            "ATED",
            "ATELY",
            "ATHER",
            "ATION",
            "AUL",
            "AVE",
            "AW",
            "B",
            "BACK",
            "BALL",
            "BE",
            "BEAT",
            "BEC",
            "BED",
            "BEL",
            "BES",
            "BIDE",
            "BIN",
            "BLE",
            "BLIC",
            "BO",
            "BR",
            "BU",
            "BUL",
            "BY",
            "C",
            "CA",
            "CAME",
            "CAR",
            "CAUSE",
            "CCO",
            "CE",
            "CELE",
            "CES",
            "CH",
            "CHIN",
            "CHO",
            "CIDENT",
            "CIOUS",
            "CK",
            "CKED",
            "CKET",
            "CLAIM",
            "CLE",
            "CO",
            "COAT",
            "COL",
            "COME",
            "CRAC",
            "CREA",
            "CRI",
            "CT",
            "CTOR",
            "CU",
            "CUR",
            "CUT",
            "D",
            "DATE",
            "DAY",
            "DDE",
            "DDING",
            "DE",
            "DEA",
            "DED",
            "DEM",
            "DEN",
            "DER",
            "DOW",
            "DOWN",
            "DUC",
            "E",
            "EACH",
            "EAK",
            "EAL",
            "EAM",
            "EAN",
            "EARN",
            "EASE",
            "EASURE",
            "EAT",
            "EAU",
            "ECI",
            "ED",
            "EDIC",
            "EEC",
            "EEK",
            "EEP",
            "EF",
            "EFI",
            "EL",
            "ELD",
            "ELF",
            "ELY",
            "EMENT",
            "EMP",
            "EMS",
            "EN",
            "ENCE",
            "END",
            "ENSIVE",
            "ENT",
            "ENTER",
            "EO",
            "EP",
            "EQUI",
            "ER",
            "ERAL",
            "ERGE",
            "ERIOUS",
            "ERR",
            "ERS",
            "ES",
            "ESE",
            "ESS",
            "EST",
            "ETI",
            "ETTE",
            "ETTY",
            "EVA",
            "EVEN",
            "EVENT",
            "EW",
            "FATHER",
            "FE",
            "FF",
            "FLE",
            "FOR",
            "FORM",
            "FORT",
            "FT",
            "FUL",
            "FULLY",
            "G",
            "GE",
            "GER",
            "GGL",
            "GIN",
            "GING",
            "GRADE",
            "GRE",
            "GU",
            "GUE",
            "H",
            "HAIR",
            "HALL",
            "HAM",
            "HAND",
            "HAV",
            "HE",
            "HINE",
            "HINS",
            "HOLD",
            "HOUSE",
            "I",
            "IAN",
            "IC",
            "ICAL",
            "ICE",
            "ICI",
            "ICKER",
            "ICO",
            "ICT",
            "ID",
            "IDE",
            "IDENT",
            "IDI",
            "IES",
            "IF",
            "IFF",
            "IFI",
            "IFT",
            "IG",
            "IGH",
            "IGHT",
            "IGN",
            "IKE",
            "IL",
            "ILD",
            "ILL",
            "ILY",
            "IM",
            "IMME",
            "IMS",
            "IN",
            "INAL",
            "INE",
            "INED",
            "INES",
            "ING",
            "INGER",
            "INI",
            "INK",
            "INNER",
            "INS",
            "INTER",
            "ION",
            "IONA",
            "IOR",
            "IP",
            "IQU",
            "IR",
            "IRE",
            "IRES",
            "IS",
            "ISGUI",
            "ISLA",
            "IT",
            "ITION",
            "ITOR",
            "ITS",
            "ITTEN",
            "ITY",
            "IV",
            "IVE",
            "IZE",
            "K",
            "KE",
            "KED",
            "L",
            "LAR",
            "LAX",
            "LAY",
            "LAZ",
            "LD",
            "LE",
            "LECT",
            "LED",
            "LEND",
            "LFA",
            "LI",
            "LICK",
            "LIE",
            "LIES",
            "LIGHT",
            "LIKE",
            "LIM",
            "LL",
            "LLEG",
            "LLEN",
            "LO",
            "LON",
            "LOR",
            "LOW",
            "LOWER",
            "LP",
            "LPH",
            "LS",
            "LU",
            "LUM",
            "LY",
            "M",
            "MA",
            "MAIN",
            "MAND",
            "MB",
            "MBER",
            "MENT",
            "MENTS",
            "MIT",
            "MITTE",
            "MP",
            "MSEL",
            "MULA",
            "N",
            "NAI",
            "NANC",
            "NCH",
            "NCI",
            "ND",
            "NDER",
            "NDS",
            "NE",
            "NERS",
            "NG",
            "NGO",
            "NIC",
            "NLY",
            "NOR",
            "NOT",
            "NOW",
            "NSTRUCTION",
            "NT",
            "NTEE",
            "NTER",
            "NUM",
            "NUT",
            "OACH",
            "OAST",
            "OAT",
            "OD",
            "ODE",
            "OES",
            "OK",
            "OL",
            "OLD",
            "OLO",
            "OM",
            "OME",
            "ON",
            "ONE",
            "ONS",
            "OO",
            "OOD",
            "OOR",
            "OP",
            "OR",
            "ORE",
            "ORG",
            "ORK",
            "ORN",
            "ORT",
            "OSE",
            "OSS",
            "OST",
            "OT",
            "OTH",
            "OTHER",
            "OTIC",
            "OUGH",
            "OUL",
            "OUNCE",
            "OUND",
            "OUR",
            "OUSI",
            "OUSLY",
            "OVER",
            "OWE",
            "OWL",
            "OWN",
            "OZ",
            "P",
            "PAIN",
            "PAR",
            "PARK",
            "PART",
            "PE",
            "PEN",
            "PEND",
            "PER",
            "PERI",
            "PH",
            "PHONE",
            "PLACE",
            "PLEAS",
            "PLIANCE",
            "PLO",
            "PON",
            "PORT",
            "PPET",
            "PRON",
            "PT",
            "QUAR",
            "QUE",
            "R",
            "RA",
            "RACE",
            "RAIN",
            "RANGE",
            "RATE",
            "RAVE",
            "RCES",
            "RE",
            "READ",
            "RED",
            "REFER",
            "RES",
            "RESP",
            "RESS",
            "RIE",
            "RIGHT",
            "RING",
            "RM",
            "RN",
            "RO",
            "ROCK",
            "ROS",
            "ROUGH",
            "ROUND",
            "ROW",
            "RS",
            "RT",
            "RUC",
            "RUGG",
            "RY",
            "S",
            "SE",
            "SELF",
            "SERVE",
            "SES",
            "SH",
            "SHIN",
            "SION",
            "SIVE",
            "SK",
            "SKET",
            "SO",
            "SON",
            "SPEC",
            "SPECT",
            "SPIT",
            "SPRIN",
            "SSER",
            "ST",
            "STER",
            "STR",
            "STRO",
            "STRUCT",
            "SW",
            "T",
            "TA",
            "TAIN",
            "TAINS",
            "TCH",
            "TE",
            "TED",
            "TELL",
            "TELY",
            "TEN",
            "TER",
            "TH",
            "THER",
            "THING",
            "THOUGH",
            "THREE",
            "TIC",
            "TICAL",
            "TING",
            "TION",
            "TIONS",
            "TIRE",
            "TITUDE",
            "TM",
            "TMENT",
            "TO",
            "TOR",
            "TORS",
            "TRACT",
            "TREE",
            "TROU",
            "TTER",
            "TTING",
            "TTLE",
            "TUALLY",
            "TURE",
            "TY",
            "U",
            "UALLY",
            "UATION",
            "UB",
            "UBB",
            "UCH",
            "UCK",
            "UCTION",
            "UD",
            "UDGE",
            "UE",
            "UG",
            "UGGE",
            "UGHT",
            "UM",
            "UMB",
            "UMI",
            "UMP",
            "UN",
            "UNIT",
            "UP",
            "UPP",
            "UR",
            "URE",
            "URS",
            "US",
            "UT",
            "V",
            "VAL",
            "VAN",
            "VE",
            "VEL",
            "VEN",
            "VER",
            "VERAL",
            "VERW",
            "VERY",
            "VES",
            "VI",
            "VIT",
            "VOR",
            "W",
            "WARD",
            "WARM",
            "WAY",
            "WAYS",
            "WHE",
            "WHERE",
            "WL",
            "WN",
            "WORE",
            "X",
            "XTRO",
            "Y",
            "ZE",
            "▁",
            "▁A",
            "▁AB",
            "▁ABLE",
            "▁ABOUT",
            "▁ABOVE",
            "▁AC",
            "▁ACC",
            "▁ACCO",
            "▁ACCOMPLISH",
            "▁ACHE",
            "▁ACT",
            "▁ACTI",
            "▁ADD",
            "▁ADV",
            "▁AGAIN",
            "▁AIR",
            "▁AL",
            "▁ALL",
            "▁ALONE",
            "▁AM",
            "▁AN",
            "▁AND",
            "▁ANY",
            "▁AP",
            "▁APPE",
            "▁APPR",
            "▁AR",
            "▁ARE",
            "▁ARM",
            "▁AROUND",
            "▁AS",
            "▁ASK",
            "▁AT",
            "▁ATTEN",
            "▁ATTITUDE",
            "▁AWAY",
            "▁B",
            "▁BA",
            "▁BACK",
            "▁BAD",
            "▁BAG",
            "▁BAN",
            "▁BANK",
            "▁BE",
            "▁BEA",
            "▁BEAR",
            "▁BEG",
            "▁BEN",
            "▁BEND",
            "▁BI",
            "▁BIG",
            "▁BIT",
            "▁BL",
            "▁BLA",
            "▁BLO",
            "▁BO",
            "▁BOOK",
            "▁BOOT",
            "▁BOOTH",
            "▁BOTH",
            "▁BOUGHT",
            "▁BOX",
            "▁BR",
            "▁BRA",
            "▁BRI",
            "▁BRO",
            "▁BROTHER",
            "▁BROUGHT",
            "▁BU",
            "▁BUN",
            "▁BUR",
            "▁BURN",
            "▁BUT",
            "▁C",
            "▁CA",
            "▁CABLE",
            "▁CAKE",
            "▁CAL",
            "▁CALL",
            "▁CAN",
            "▁CAR",
            "▁CARR",
            "▁CAS",
            "▁CAT",
            "▁CH",
            "▁CHA",
            "▁CHARLIE",
            "▁CHE",
            "▁CHEE",
            "▁CHO",
            "▁CL",
            "▁CLA",
            "▁CLEA",
            "▁CO",
            "▁COLD",
            "▁COM",
            "▁COME",
            "▁COMM",
            "▁COMP",
            "▁CON",
            "▁CONFI",
            "▁CONS",
            "▁CONT",
            "▁CONTAIN",
            "▁CONTR",
            "▁CONTRA",
            "▁COU",
            "▁COVER",
            "▁CRA",
            "▁CREA",
            "▁CUT",
            "▁D",
            "▁DA",
            "▁DAMAGE",
            "▁DAR",
            "▁DARK",
            "▁DAY",
            "▁DE",
            "▁DEAD",
            "▁DEC",
            "▁DEER",
            "▁DEF",
            "▁DEGREE",
            "▁DEL",
            "▁DEP",
            "▁DES",
            "▁DESERVE",
            "▁DI",
            "▁DID",
            "▁DIR",
            "▁DIS",
            "▁DISAPPOINT",
            "▁DISC",
            "▁DISPLAY",
            "▁DISTR",
            "▁DO",
            "▁DOCK",
            "▁DON",
            "▁DOU",
            "▁DOWN",
            "▁DR",
            "▁DRE",
            "▁DRESS",
            "▁DRI",
            "▁DRIFT",
            "▁DRO",
            "▁DU",
            "▁E",
            "▁EACH",
            "▁EAR",
            "▁EAS",
            "▁EAT",
            "▁ECONOM",
            "▁EI",
            "▁EL",
            "▁EN",
            "▁EVEN",
            "▁EVER",
            "▁EVERY",
            "▁EX",
            "▁EXA",
            "▁EXC",
            "▁EXCE",
            "▁EXP",
            "▁EXPECT",
            "▁EXPERI",
            "▁EXPERIMENT",
            "▁F",
            "▁FA",
            "▁FAIL",
            "▁FAMIL",
            "▁FAT",
            "▁FE",
            "▁FEAR",
            "▁FEE",
            "▁FEEL",
            "▁FELL",
            "▁FI",
            "▁FIE",
            "▁FILL",
            "▁FIN",
            "▁FIRST",
            "▁FIT",
            "▁FIVE",
            "▁FL",
            "▁FLOOR",
            "▁FLOW",
            "▁FLOWER",
            "▁FO",
            "▁FOR",
            "▁FORK",
            "▁FORM",
            "▁FOUR",
            "▁FOX",
            "▁FR",
            "▁FRE",
            "▁FRIEND",
            "▁FROM",
            "▁FRU",
            "▁FU",
            "▁FULL",
            "▁FUN",
            "▁G",
            "▁GA",
            "▁GAL",
            "▁GAS",
            "▁GE",
            "▁GEN",
            "▁GI",
            "▁GIN",
            "▁GLI",
            "▁GLO",
            "▁GO",
            "▁GOLF",
            "▁GOOD",
            "▁GRA",
            "▁GRAD",
            "▁GRAN",
            "▁GRAND",
            "▁GRANDFATHER",
            "▁GRE",
            "▁GREA",
            "▁GREAT",
            "▁GRO",
            "▁GROW",
            "▁GUAR",
            "▁H",
            "▁HAD",
            "▁HAIR",
            "▁HAN",
            "▁HAND",
            "▁HAR",
            "▁HARD",
            "▁HARM",
            "▁HAS",
            "▁HAT",
            "▁HAVE",
            "▁HE",
            "▁HEAR",
            "▁HEART",
            "▁HEAT",
            "▁HER",
            "▁HERE",
            "▁HI",
            "▁HID",
            "▁HIGH",
            "▁HIM",
            "▁HIR",
            "▁HIS",
            "▁HO",
            "▁HOR",
            "▁HOTEL",
            "▁HOUS",
            "▁HOUSE",
            "▁HU",
            "▁HUM",
            "▁I",
            "▁IMMEDIATE",
            "▁IMP",
            "▁IN",
            "▁INJUR",
            "▁INNOCEN",
            "▁INSTRU",
            "▁IS",
            "▁IT",
            "▁J",
            "▁JA",
            "▁JOB",
            "▁JU",
            "▁JUDGE",
            "▁JUMP",
            "▁KE",
            "▁KEEP",
            "▁KI",
            "▁KITTEN",
            "▁KNE",
            "▁KNEW",
            "▁KNI",
            "▁KNO",
            "▁KNOW",
            "▁L",
            "▁LA",
            "▁LAC",
            "▁LARGE",
            "▁LATER",
            "▁LAW",
            "▁LE",
            "▁LEA",
            "▁LEAK",
            "▁LEG",
            "▁LEGISLAT",
            "▁LEND",
            "▁LI",
            "▁LIE",
            "▁LIFE",
            "▁LIG",
            "▁LIKE",
            "▁LIT",
            "▁LITT",
            "▁LIV",
            "▁LIVE",
            "▁LO",
            "▁LONG",
            "▁LOOK",
            "▁LOS",
            "▁LOT",
            "▁LOVE",
            "▁LOW",
            "▁LU",
            "▁M",
            "▁MA",
            "▁MADE",
            "▁MAKE",
            "▁MAN",
            "▁MAR",
            "▁MARRI",
            "▁MAS",
            "▁MAY",
            "▁ME",
            "▁MEAT",
            "▁MEN",
            "▁MI",
            "▁MILL",
            "▁MIN",
            "▁MINU",
            "▁MIS",
            "▁MO",
            "▁MONEY",
            "▁MORE",
            "▁MU",
            "▁MUCH",
            "▁MUS",
            "▁MUSIC",
            "▁MUT",
            "▁MY",
            "▁MYSELF",
            "▁N",
            "▁NA",
            "▁NE",
            "▁NEA",
            "▁NEAR",
            "▁NEED",
            "▁NEEDED",
            "▁NEW",
            "▁NICE",
            "▁NIGHT",
            "▁NINE",
            "▁NINETY",
            "▁NO",
            "▁NOT",
            "▁NOW",
            "▁NU",
            "▁O",
            "▁OBS",
            "▁OBSERVE",
            "▁OBTAIN",
            "▁OC",
            "▁OF",
            "▁OFF",
            "▁OIL",
            "▁OLD",
            "▁ON",
            "▁ONE",
            "▁ONLY",
            "▁OR",
            "▁OUT",
            "▁OVER",
            "▁OWN",
            "▁OWNER",
            "▁P",
            "▁PA",
            "▁PAIN",
            "▁PAINT",
            "▁PAN",
            "▁PAP",
            "▁PART",
            "▁PAST",
            "▁PE",
            "▁PEA",
            "▁PER",
            "▁PET",
            "▁PETT",
            "▁PHONE",
            "▁PI",
            "▁PIC",
            "▁PICK",
            "▁PICKPOCKET",
            "▁PIT",
            "▁PL",
            "▁PLACE",
            "▁PLAY",
            "▁PLAYED",
            "▁PLEASE",
            "▁PLEASURE",
            "▁PO",
            "▁POCKET",
            "▁POPULA",
            "▁POPULAR",
            "▁PORC",
            "▁PORCH",
            "▁PORT",
            "▁POS",
            "▁POST",
            "▁POT",
            "▁PR",
            "▁PRACTICAL",
            "▁PRE",
            "▁PRES",
            "▁PRI",
            "▁PRO",
            "▁PROGRAM",
            "▁PROP",
            "▁PROSPECT",
            "▁PROV",
            "▁PU",
            "▁QU",
            "▁QUI",
            "▁QUICK",
            "▁QUICKER",
            "▁R",
            "▁RA",
            "▁RAG",
            "▁RAI",
            "▁RAKE",
            "▁RANGE",
            "▁RE",
            "▁REA",
            "▁READ",
            "▁REAL",
            "▁RED",
            "▁REFLE",
            "▁REGULA",
            "▁REGULAR",
            "▁RELAX",
            "▁REPORT",
            "▁REQU",
            "▁REQUIRE",
            "▁RESE",
            "▁RESULT",
            "▁RI",
            "▁RID",
            "▁RIDE",
            "▁RIGHT",
            "▁RISE",
            "▁RO",
            "▁ROCK",
            "▁ROM",
            "▁ROO",
            "▁RU",
            "▁S",
            "▁SAID",
            "▁SAT",
            "▁SAW",
            "▁SCHO",
            "▁SCHOOL",
            "▁SCOR",
            "▁SCR",
            "▁SCREE",
            "▁SE",
            "▁SEA",
            "▁SEE",
            "▁SEED",
            "▁SELECT",
            "▁SELL",
            "▁SERV",
            "▁SERVE",
            "▁SEW",
            "▁SH",
            "▁SHA",
            "▁SHE",
            "▁SHEE",
            "▁SHELL",
            "▁SHO",
            "▁SHOO",
            "▁SHORT",
            "▁SHOU",
            "▁SHOW",
            "▁SI",
            "▁SIDE",
            "▁SIGH",
            "▁SIL",
            "▁SIN",
            "▁SING",
            "▁SIT",
            "▁SKI",
            "▁SKILL",
            "▁SL",
            "▁SLI",
            "▁SLOWLY",
            "▁SMALL",
            "▁SMO",
            "▁SN",
            "▁SNO",
            "▁SO",
            "▁SOCIAL",
            "▁SOL",
            "▁SOLD",
            "▁SOME",
            "▁SOU",
            "▁SOUL",
            "▁SP",
            "▁SPA",
            "▁SPAR",
            "▁SPARK",
            "▁SPEAK",
            "▁SPLI",
            "▁SPR",
            "▁SPRA",
            "▁SPRIN",
            "▁ST",
            "▁STA",
            "▁STAT",
            "▁STATE",
            "▁STE",
            "▁STEE",
            "▁STEEP",
            "▁STI",
            "▁STICK",
            "▁STOR",
            "▁STORE",
            "▁STR",
            "▁STRA",
            "▁STREET",
            "▁STRETCH",
            "▁STRONG",
            "▁STU",
            "▁STUDENTS",
            "▁SU",
            "▁SUBTRACT",
            "▁SUC",
            "▁SUIT",
            "▁SUN",
            "▁SUPP",
            "▁SUR",
            "▁SW",
            "▁SWA",
            "▁T",
            "▁TA",
            "▁TAK",
            "▁TAKE",
            "▁TAL",
            "▁TE",
            "▁TEA",
            "▁TELL",
            "▁TH",
            "▁THAT",
            "▁THE",
            "▁THERE",
            "▁THEY",
            "▁THI",
            "▁THINK",
            "▁THO",
            "▁THOUGH",
            "▁THOUGHT",
            "▁THREA",
            "▁THREE",
            "▁THROUGH",
            "▁TI",
            "▁TICK",
            "▁TIME",
            "▁TIP",
            "▁TO",
            "▁TOO",
            "▁TRA",
            "▁TRAD",
            "▁TRADE",
            "▁TRAI",
            "▁TRAIN",
            "▁TRANS",
            "▁TRI",
            "▁TRIP",
            "▁TRO",
            "▁TRY",
            "▁TW",
            "▁TWI",
            "▁TWO",
            "▁U",
            "▁UN",
            "▁UNI",
            "▁UP",
            "▁UPB",
            "▁UR",
            "▁URGE",
            "▁US",
            "▁USE",
            "▁VA",
            "▁VAL",
            "▁VI",
            "▁VO",
            "▁VOCA",
            "▁VOICE",
            "▁W",
            "▁WA",
            "▁WALK",
            "▁WALL",
            "▁WANT",
            "▁WARM",
            "▁WAS",
            "▁WATER",
            "▁WAY",
            "▁WE",
            "▁WEED",
            "▁WEEK",
            "▁WEL",
            "▁WELL",
            "▁WENT",
            "▁WERE",
            "▁WH",
            "▁WHEN",
            "▁WHI",
            "▁WHITE",
            "▁WHO",
            "▁WHY",
            "▁WI",
            "▁WICKE",
            "▁WILL",
            "▁WIN",
            "▁WISH",
            "▁WIT",
            "▁WITH",
            "▁WO",
            "▁WOO",
            "▁WOOL",
            "▁WOR",
            "▁WORK",
            "▁WR",
            "▁WRITE",
            "▁YARD",
            "▁YE",
            "▁YEAR",
            "▁YEARS",
            "▁YELL",
            "▁YELLOW",
            "▁YET",
            "▁YOU",
            "▁YOUR",
            "▁Z",
            "▁ZE",
            "<eos>"
        ],
        "config": "conf/train.yaml",
        "config2": null,
        "config3": null,
        "context_residual": false,
        "criterion": "loss",
        "ctc_type": "warpctc",
        "ctc_weight": 0.3,
        "debugdir": "exp/train_set_pytorch_train_specaug",
        "debugmode": 1,
        "dec_init": "pretrained/medium/model.val5.avg.best",
        "dec_init_mods": [
            "att.",
            " dec."
        ],
        "decoder_mode": "AR",
        "dict": "data/lang_char/train_set_unigram1230_units.txt",
        "dlayers": 6,
        "dropout_rate": 0.1,
        "dunits": 2048,
        "early_stop_criterion": "validation/main/acc",
        "elayers": 12,
        "enc_init": "pretrained/medium/model.val5.avg.best",
        "enc_init_mods": [
            "enc.enc."
        ],
        "epochs": 150,
        "eps": 1e-08,
        "eps_decay": 0.01,
        "eunits": 2048,
        "fbank_fmax": null,
        "fbank_fmin": 0.0,
        "fbank_fs": 16000,
        "freeze_mods": null,
        "grad_clip": 5.0,
        "grad_noise": false,
        "ldconv_decoder_kernel_length": "11_13_15_17_19_21",
        "ldconv_encoder_kernel_length": "21_23_25_27_29_31_33_35_37_39_41_43",
        "ldconv_usebias": false,
        "lm_weight": 0.1,
        "lsm_weight": 0.1,
        "maxlen_in": 800,
        "maxlen_out": 150,
        "maxlenratio": 0.0,
        "minibatches": 0,
        "minlenratio": 0.0,
        "model_module": "espnet.nets.pytorch_backend.e2e_asr_transformer_recons:E2E",
        "mtlalpha": 0.3,
        "n_iter_processes": 0,
        "n_mels": 80,
        "nbest": 1,
        "ngpu": 2,
        "num_encs": 1,
        "num_save_attention": 3,
        "num_save_ctc": 3,
        "num_spkrs": 1,
        "opt": "noam",
        "outdir": "exp/train_set_pytorch_train_specaug/results",
        "patience": 0,
        "penalty": 0.0,
        "preprocess_conf": "conf/specaug.yaml",
        "pretrain": null,
        "ref_channel": -1,
        "report_cer": false,
        "report_interval_iters": 5,
        "report_wer": false,
        "resume": null,
        "rnnlm": null,
        "rnnlm_conf": null,
        "save_interval_iters": 0,
        "seed": 1,
        "sortagrad": 0,
        "stats_file": null,
        "sym_blank": "<blank>",
        "sym_space": "<space>",
        "tensorboard_dir": "tensorboard/train_set_pytorch_train_specaug",
        "threshold": 0.0001,
        "train_dtype": "float32",
        "train_json": "dump/train_set/deltafalse/data_unigram1230.json",
        "transformer_attn_dropout_rate": 0.0,
        "transformer_decoder_selfattn_layer_type": "selfattn",
        "transformer_encoder_selfattn_layer_type": "selfattn",
        "transformer_init": "pytorch",
        "transformer_input_layer": "conv2d",
        "transformer_length_normalized_loss": 0,
        "transformer_lr": 10.0,
        "transformer_warmup_steps": 25000,
        "use_beamformer": true,
        "use_dnn_mask_for_wpe": false,
        "use_frontend": false,
        "use_wpe": false,
        "uttmvn_norm_means": true,
        "uttmvn_norm_vars": false,
        "valid_json": "dump/valid_set/deltafalse/data_unigram1230.json",
        "verbose": 0,
        "wdropout_rate": 0.0,
        "weight_decay": 0.0,
        "wlayers": 2,
        "wpe_delay": 3,
        "wpe_taps": 5,
        "wprojs": 300,
        "wshare": 4,
        "wtype": "blstmp",
        "wunits": 300
    }
]